{
  "attachmentObjectFieldExternalReferenceCodes": [],
  "attachmentObjectFieldIds": [],
  "body": {},
  "description": "Sends email notification to users when their distributor application is approved.",
  "editorType": "richText",
  "externalReferenceCode": "DISTRIBUTOR_APPLICATION_APPROVED_CUSTOMER_EMAIL",
  "name": "Email_ApplicationApproved_Customer",
  "name_i18n": {
    "en_US": "Email_ApplicationApproved_Customer"
  },
  "objectDefinitionExternalReferenceCode": "",
  "objectDefinitionId": 0,
  "recipientType": "email",
  "recipients": [
    {
      "cc": "",
      "bcc": "",
      "fromName": {
        "en_US": "Liferay Learn"
      },
      "from": "learn@liferay.com",
      "to": {
        "en_US": "[%DISTRIBUTORAPPLICATION_APPLICANTEMAIL%]"
      }
    }
  ],
  "subject": {
    "en_US": "Your application was approved!"
  },
  "type": "email",
  "typeLabel": "Email"
}
