{"name_i18n":{"en-US":"Ticket Statuses"},"name":"Ticket Statuses","listTypeEntries":[{"name_i18n":{"en-US":"Open"},"name":"Open","type":"","key":"open","externalReferenceCode":"open-status"},{"name_i18n":{"en-US":"Verifying"},"name":"Verifying","type":"","key":"verifying","externalReferenceCode":"verifying-status"},{"name_i18n":{"en-US":"Queued"},"name":"Queued","type":"","key":"queued","externalReferenceCode":"queued-status"},{"name_i18n":{"en-US":"In Progress"},"name":"In Progress","type":"","key":"inProgress","externalReferenceCode":"in-progress-status"},{"name_i18n":{"en-US":"Answered"},"name":"Answered","type":"","key":"answered","externalReferenceCode":"answered-status"},{"name_i18n":{"en-US":"Escalated"},"name":"Escalated","type":"","key":"escalated","externalReferenceCode":"escalated-status"},{"name_i18n":{"en-US":"In Review"},"name":"In Review","type":"","key":"inReview","externalReferenceCode":"in-review-status"},{"name_i18n":{"en-US":"Waiting"},"name":"Waiting","type":"","key":"waiting","externalReferenceCode":"waiting-status"},{"name_i18n":{"en-US":"Closed"},"name":"Closed","type":"","key":"closed","externalReferenceCode":"closed-status"}],"externalReferenceCode":"list-ticket-statuses"}